modules/Registers.v
/*
    Registers:
      A selection of Registers, which will latch data on the rising edge of the clock
      input when the latch signal is also high. The content of the register is output
      onto the output pins when the enable signal is high, otherwise the output pins
      are in a high capacitance state.

    Usage:
      Register_Buffered #(8) regA(bus[7:0], data_push, enable, latch, clk);
*/
module Register_Buffered(
    output [width - 1:0] data_out,
    input [width - 1:0] data_in,
    input enable,
    input latch,
    input clk);

  parameter width = 4;

  reg [width - 1:0] data_internal = {(width) {1'hX}};

  assign data_out = (enable == 1) ? data_internal : {(width) {1'hZ}};

  always @ (posedge clk) begin
    if(latch) begin
      data_internal = data_in;
    end
  end
endmodule

module Register_Counter_Buffered(
    output [width - 1:0] data_out,
    input [width - 1:0] data_in,
    input enable,
    input latch,
    input increment,
    input clk);

  parameter width = 4;

  reg [width - 1:0] data_internal = {(width) {1'hX}};

  assign data_out = (enable == 1) ? data_internal : {(width) {1'hZ}};

  always @ (posedge clk) begin
    if(latch) begin
      data_internal = data_in;
    end
    if(!latch && increment) begin
      data_internal = data_internal + 1;
    end
  end
endmodule

modules/RAM.v
/*
    RAM:
      Basic memory chip.

    Usage:
      RAM_Volatile #(4, 8) ram(bus[7:0], data_push[3:0], OE, WE, clk);
*/
module RAM_Volatile(
  inout [dataWidth - 1:0] data,
  input [addressWidth -1:0] address,
  input OE,
  input WE,
  input clk);

  parameter addressWidth = 4;
  parameter dataWidth = 8;

  reg [dataWidth - 1:0] internalData [0:(1 << addressWidth) - 1];

  assign data = (OE && !WE) ? internalData[address] : {dataWidth{1'bZ}};

  always @ (posedge clk) begin
    if(WE && !OE) begin
      internalData[address] = data;
    end
  end
endmodule

modules/CPU.v
module CPU(
  inout [busWidth - 1:0] bus,
  input clk);

  parameter busWidth = 16;

  // Control
  reg MAR_OE = 0;
  reg MAR_LE = 0;

  reg RAM_OE = 0;
  reg RAM_WE = 0;

  // Nets
  wire [15:0] MAR_RAM; // Connects MAR output to RAM address

  Register_Buffered #(16) MAR(MAR_RAM[15:0], bus[15:0], MAR_OE, MAR_LE, clk);
  RAM_Volatile #(16, 8) RAM(bus[15:0], MAR_RAM[15:0], RAM_OE, RAM_WE, clk);

endmodule

test.v
`include "modules/Registers.v"
`include "modules/RAM.v"
`include "modules/CPU.v"

module test;

  wire [15:0] bus;

  reg clk;

  CPU cpu(bus, clk);

  reg [7:0] busSet = 8'h11;
  assign bus[7:0] = busSet;

  reg enable = 0;
  reg latch = 0;
  reg increment = 0;

  Register_Counter_Buffered #(8) regA(bus[15:8], bus[7:0], enable, latch, increment, clk);

  initial begin
    $dumpvars(0, test);
    clk = 0;

    busSet = 8'h22;

    #10;
    enable = 1;
    #2;
    enable = 0;

    #5;
    latch = 1;
    #2;
    latch = 0;

    #5;
    enable = 1;
    #2;
    enable = 0;

    #5;
    increment = 1;
    #3;
    increment = 0;

    #5;
    enable = 1;
    #2;
    enable = 0;


    #100;


    $finish;
  end

  always begin
    #1;
    clk = ~clk;
  end

endmodule

dump.vcd
$date
	Fri Apr  7 19:26:04 2017
$end
$version
	Icarus Verilog
$end
$timescale
	1s
$end
$scope module test $end
$var wire 16 ! bus [15:0] $end
$var reg 8 " busSet [7:0] $end
$var reg 1 # clk $end
$var reg 1 $ enable $end
$var reg 1 % increment $end
$var reg 1 & latch $end
$scope module cpu $end
$var wire 16 ' MAR_RAM [15:0] $end
$var wire 16 ( bus [15:0] $end
$var wire 1 ) clk $end
$var reg 1 * MAR_LE $end
$var reg 1 + MAR_OE $end
$var reg 1 , RAM_OE $end
$var reg 1 - RAM_WE $end
$scope module MAR $end
$var wire 1 ) clk $end
$var wire 16 . data_in [15:0] $end
$var wire 16 / data_out [15:0] $end
$var wire 1 0 enable $end
$var wire 1 1 latch $end
$var reg 16 2 data_internal [15:0] $end
$upscope $end
$scope module RAM $end
$var wire 1 3 OE $end
$var wire 1 4 WE $end
$var wire 16 5 address [15:0] $end
$var wire 1 ) clk $end
$var wire 8 6 data [7:0] $end
$upscope $end
$upscope $end
$scope module regA $end
$var wire 1 ) clk $end
$var wire 8 7 data_in [7:0] $end
$var wire 8 8 data_out [7:0] $end
$var wire 1 9 enable $end
$var wire 1 : increment $end
$var wire 1 ; latch $end
$var reg 8 < data_internal [7:0] $end
$upscope $end
$upscope $end
$enddefinitions $end
#0
$dumpvars
bx <
0;
0:
09
bz 8
b100010 7
b100010 6
bz 5
04
03
bx 2
01
00
bz /
bz00100010 .
0-
0,
0+
0*
0)
bz00100010 (
bz '
0&
0%
0$
0#
b100010 "
bz00100010 !
$end
#1
1#
1)
#2
0#
0)
#3
1#
1)
#4
0#
0)
#5
1#
1)
#6
0#
0)
#7
1#
1)
#8
0#
0)
#9
1#
1)
#10
bx00100010 !
bx00100010 (
bx00100010 .
bx 8
0#
0)
1$
19
#11
1#
1)
#12
bz00100010 !
bz00100010 (
bz00100010 .
bz 8
0#
0)
0$
09
#13
1#
1)
#14
0#
0)
#15
1#
1)
#16
0#
0)
#17
b100010 <
1#
1)
1&
1;
#18
0#
0)
#19
1#
1)
0&
0;
#20
0#
0)
#21
1#
1)
#22
0#
0)
#23
1#
1)
#24
b10001000100010 !
b10001000100010 (
b10001000100010 .
b100010 8
0#
0)
1$
19
#25
1#
1)
#26
bz00100010 !
bz00100010 (
bz00100010 .
bz 8
0#
0)
0$
09
#27
1#
1)
#28
0#
0)
#29
1#
1)
#30
0#
0)
#31
b100011 <
1#
1)
1%
1:
#32
0#
0)
#33
b100100 <
1#
1)
#34
0#
0)
0%
0:
#35
1#
1)
#36
0#
0)
#37
1#
1)
#38
0#
0)
#39
b10010000100010 !
b10010000100010 (
b10010000100010 .
b100100 8
1#
1)
1$
19
#40
0#
0)
#41
bz00100010 !
bz00100010 (
bz00100010 .
bz 8
1#
1)
0$
09
