modules/Registers.v
/*
    Registers:
      A selection of Registers, which will latch data on the rising edge of the clock
      input when the latch signal is also high. The content of the register is output
      onto the output pins when the enable signal is high, otherwise the output pins
      are in a high capacitance state.
*/
module Register_4Bit_Buffered(
    output [3:0] data_out,
    input [3:0] data_in,
    input enable,
    input latch,
    input clk);

  reg [3:0] data_internal = 4'hX;

  assign data_out = (enable == 1) ? data_internal : 4'hZ;

  always @ (posedge clk) begin
    if(latch) begin
      data_internal = data_in;
    end
  end
endmodule

module Register_8Bit_Buffered(
    output [7:0] data_out,
    input [7:0] data_in,
    input enable,
    input latch,
    input clk);

  reg [7:0] data_internal = 8'hXX;

  assign data_out = (enable == 1) ? data_internal : 8'hZZ;

  always @ (posedge clk) begin
    if(latch) begin
      data_internal = data_in;
    end
  end
endmodule

module Register_16Bit_Buffered(
    output [15:0] data_out,
    input [15:0] data_in,
    input enable,
    input latch,
    input clk);

  reg [15:0] data_internal = 16'hXXXX;

  assign data_out = (enable == 1) ? data_internal : 16'hZZZZ;

  always @ (posedge clk) begin
    if(latch) begin
      data_internal = data_in;
    end
  end
endmodule

test.v
`include "modules/Registers.v"

module test;

  wire [15:0] bus;

  reg clk, enable0, latch0, enable1, latch1;
  reg [15:0] data_push0 = 16'h5B4E;
  reg [3:0] data_push1 = 4'hA;

  Register_16Bit_Buffered regA(bus, data_push0, enable0, latch0, clk);
  Register_4Bit_Buffered regB(bus[3:0], data_push1, enable1, latch1, clk);

  initial begin

    $dumpvars(4, test);

    clk = 0;
    enable0 = 0;
    latch0 = 0;
    enable1 = 0;
    latch1 = 0;

    #11;
    latch0 = 1;
    #6;
    latch0 = 0;

    #20;
    enable0 = 1;
    #6;
    enable0 = 0;




    #11;
    latch1 = 1;
    #6;
    latch1 = 0;

    #20;
    enable1 = 1;
    #6;
    enable1 = 0;

    #100;


    $finish;
  end

  always begin
    #2;
    clk = ~clk;
  end

endmodule

dump.vcd
$date
	Wed Apr  5 18:26:48 2017
$end
$version
	Icarus Verilog
$end
$timescale
	1s
$end
$scope module test $end
$var wire 16 ! bus [15:0] $end
$var reg 1 " clk $end
$var reg 16 # data_push0 [15:0] $end
$var reg 4 $ data_push1 [3:0] $end
$var reg 1 % enable0 $end
$var reg 1 & enable1 $end
$var reg 1 ' latch0 $end
$var reg 1 ( latch1 $end
$scope module regA $end
$var wire 1 ) clk $end
$var wire 16 * data_in [15:0] $end
$var wire 16 + data_out [15:0] $end
$var wire 1 , enable $end
$var wire 1 - latch $end
$var reg 16 . data_internal [15:0] $end
$upscope $end
$scope module regB $end
$var wire 1 ) clk $end
$var wire 4 / data_in [3:0] $end
$var wire 4 0 data_out [3:0] $end
$var wire 1 1 enable $end
$var wire 1 2 latch $end
$var reg 4 3 data_internal [3:0] $end
$upscope $end
$upscope $end
$enddefinitions $end
#0
$dumpvars
bx 3
02
01
bz 0
b1010 /
bx .
0-
0,
bz +
b101101101001110 *
0)
0(
0'
0&
0%
b1010 $
b101101101001110 #
0"
bz !
$end
#2
1"
1)
#4
0"
0)
#6
1"
1)
#8
0"
0)
#10
1"
1)
#11
1'
1-
#12
0"
0)
#14
b101101101001110 .
1"
1)
#16
0"
0)
#17
0'
0-
#18
1"
1)
#20
0"
0)
#22
1"
1)
#24
0"
0)
#26
1"
1)
#28
0"
0)
#30
1"
1)
#32
0"
0)
#34
1"
1)
#36
0"
0)
#37
b101101101001110 !
b101101101001110 +
1%
1,
#38
1"
1)
#40
0"
0)
#42
1"
1)
#43
bz !
bz +
0%
0,
#44
0"
0)
#46
1"
1)
#48
0"
0)
#50
1"
1)
#52
0"
0)
#54
b1010 3
1"
1)
1(
12
#56
0"
0)
#58
1"
1)
#60
0"
0)
0(
02
#62
1"
1)
#64
0"
0)
#66
1"
1)
#68
0"
0)
#70
1"
1)
#72
0"
0)
#74
1"
1)
#76
0"
0)
#78
1"
1)
#80
b1010 0
bz1010 !
bz1010 +
0"
0)
1&
11
#82
1"
1)
#84
0"
0)
#86
bz 0
bz !
bz +
1"
1)
0&
01
